setup.py
webspanner/__init__.py
webspanner/app.py
webspanner/client.py
webspanner/exceptions.py
webspanner/handlers.py
webspanner/log.py
webspanner/request.py
webspanner/response.py
webspanner/utils.py
webspanner.egg-info/PKG-INFO
webspanner.egg-info/SOURCES.txt
webspanner.egg-info/dependency_links.txt
webspanner.egg-info/requires.txt
webspanner.egg-info/top_level.txt