Metadata-Version: 1.0
Name: webspanner
Version: 0.1.0
Summary: Spanner is a micro web framework based on asyncio inspired by Flask & Express.js.
Home-page: UNKNOWN
Author: Simon Chan
Author-email: cdzos97@gmail.com
License: MIT License
Keywords: asyncio,server,web
Platform: any
